CHANGES.txt
LICENSE.txt
MANIFEST.in
README.rst
requirements-dev.txt
requirements-testing.txt
setup.py
django_response_timeout.egg-info/PKG-INFO
django_response_timeout.egg-info/SOURCES.txt
django_response_timeout.egg-info/dependency_links.txt
django_response_timeout.egg-info/requires.txt
django_response_timeout.egg-info/top_level.txt
response_timeout/__init__.py
response_timeout/middleware.py
test/__init__.py
test/settings.py
test/test_full_stack.py
test/test_middleware.py
test/urls.py