Metadata-Version: 1.1
Name: django-response-timeout
Version: 0.1.0
Summary: Django global response timeout middleware
Home-page: https://www.github.com/saulshanabrook/django-response-timeout
Author: Saul Shanabrook
Author-email: s.shanabrook@gmail.com
License: LICENSE.txt
Platform: UNKNOWN
Classifier: Development Status :: 5 - Production/Stable
Classifier: Framework :: Django
Classifier: Intended Audience :: Developers
Classifier: License :: OSI Approved :: MIT License
Classifier: Natural Language :: English
Classifier: Programming Language :: Python :: 2
Classifier: Programming Language :: Python :: 2.6
Classifier: Programming Language :: Python :: 2.7
Classifier: Programming Language :: Python :: 3
Classifier: Programming Language :: Python :: 3.2
Classifier: Programming Language :: Python :: 3.3
Classifier: Topic :: Software Development :: Libraries
